aliyunsdkivision/__init__.py
aliyunsdkivision/endpoint.py
aliyunsdkivision/request/__init__.py
aliyunsdkivision/request/v20190308/CreateFaceGroupRequest.py
aliyunsdkivision/request/v20190308/CreateFilePredictRequest.py
aliyunsdkivision/request/v20190308/CreateStreamPredictRequest.py
aliyunsdkivision/request/v20190308/DeleteFaceGroupRequest.py
aliyunsdkivision/request/v20190308/DeleteFilePredictRequest.py
aliyunsdkivision/request/v20190308/DeleteStreamPredictRequest.py
aliyunsdkivision/request/v20190308/DescribeFaceGroupsRequest.py
aliyunsdkivision/request/v20190308/DescribeStreamPredictResultRequest.py
aliyunsdkivision/request/v20190308/DescribeStreamPredictsRequest.py
aliyunsdkivision/request/v20190308/GetAlgorithmDetailRequest.py
aliyunsdkivision/request/v20190308/GetAlgorithmHistogramsRequest.py
aliyunsdkivision/request/v20190308/ImagePredictRequest.py
aliyunsdkivision/request/v20190308/ListMyAlgorithmRequest.py
aliyunsdkivision/request/v20190308/PredictPictureRequest.py
aliyunsdkivision/request/v20190308/RegisterFaceRequest.py
aliyunsdkivision/request/v20190308/SearchFaceRequest.py
aliyunsdkivision/request/v20190308/StartStreamPredictRequest.py
aliyunsdkivision/request/v20190308/StopStreamPredictRequest.py
aliyunsdkivision/request/v20190308/UnregisterFaceRequest.py
aliyunsdkivision/request/v20190308/__init__.py
aliyun_python_sdk_ivision-1.2.1.dist-info/LICENSE
aliyun_python_sdk_ivision-1.2.1.dist-info/METADATA
aliyun_python_sdk_ivision-1.2.1.dist-info/WHEEL
aliyun_python_sdk_ivision-1.2.1.dist-info/top_level.txt
aliyun_python_sdk_ivision-1.2.1.dist-info/RECORD
